COPYING.txt
MANIFEST.in
README.md
setup.cfg
setup.py
tools4py/__init__.py
tools4py/parallel_tools.py
tools4py.egg-info/PKG-INFO
tools4py.egg-info/SOURCES.txt
tools4py.egg-info/dependency_links.txt
tools4py.egg-info/requires.txt
tools4py.egg-info/top_level.txt