Metadata-Version: 1.1
Name: tools4py
Version: 0.1.1
Summary: Tools. For Python.
Home-page: https://bitbucket.org/samskillman/tools4py
Author: Samuel Skillman
Author-email: samskillman@gmail.com
License: MIT
Platform: UNKNOWN
Classifier: Programming Language :: Python
Classifier: Topic :: Software Development :: Libraries :: Python Modules
